ncluster/__init__.py
ncluster/_version.py
ncluster/aws_backend.py
ncluster/aws_create_resources.py
ncluster/aws_delete_resources.py
ncluster/aws_util.py
ncluster/backend.py
ncluster/crash_python.py
ncluster/local_backend.py
ncluster/ncluster.py
ncluster/ncluster_cloud_setup.py
ncluster/ncluster_cloud_wipe.py
ncluster/ncluster_globals.py
ncluster/old_backend.py
ncluster/old_util.py
ncluster/test.py
ncluster/tmux_backend.py
ncluster/util.py
ncluster-0.1.91.data/scripts/aws_create_resources.py
ncluster-0.1.91.data/scripts/aws_delete_resources.py
ncluster-0.1.91.data/scripts/ncluster
ncluster-0.1.91.data/scripts/ncluster_cloud_setup.py
ncluster-0.1.91.data/scripts/ncluster_cloud_wipe.py
ncluster-0.1.91.data/scripts/nsync
ncluster-0.1.91.data/scripts/sync.py
ncluster-0.1.91.dist-info/LICENSE
ncluster-0.1.91.dist-info/METADATA
ncluster-0.1.91.dist-info/WHEEL
ncluster-0.1.91.dist-info/top_level.txt
ncluster-0.1.91.dist-info/RECORD
