Metadata-Version: 2.1
Name: ncluster
Version: 0.1.91
Summary: Lightweight interface to launching jobs in the cloud
Home-page: https://github.com/yaroslavvb/ncluster
Author: Yaroslav Bulatov, Andrew Shaw, Ben Mann
Author-email: yaroslavvb@gmail.com
License: UNKNOWN
Platform: UNKNOWN
Classifier: Programming Language :: Python :: 3
Classifier: License :: OSI Approved :: MIT License
Classifier: Operating System :: OS Independent
Requires-Python: >= 3.6
Requires-Dist: botocore
Requires-Dist: boto3 (>=1.9.159)
Requires-Dist: boto3-type-annotations
Requires-Dist: cryptography
Requires-Dist: paramiko
Requires-Dist: portalocker
Requires-Dist: portpicker
Requires-Dist: pytz
Requires-Dist: wandb
